[
  { "name": "af2l1_1",  "pair": [90, 20],  "alg": "L' U' L U R U' R'" },
  { "name": "af2l1_2",  "pair": [106, 6],  "alg": "L U' L' U' R U' R'" },
  { "name": "af2l1_3",  "pair": [105, 36],  "alg": "R' U' R2 U2 R'" },
  { "name": "af2l1_4",  "pair": [154, 20],  "alg": "U2 L' U L U' R U R'" },
  { "name": "af2l1_5",  "pair": [170, 6],  "alg": "L U L' U R U R'" },
  { "name": "af2l1_6",  "pair": [169, 36],  "alg": "U2 R' U R U R U R'" },
  { "name": "af2l1_7",  "pair": [26, 20],  "alg": "U' L' U L R U' R'" },
  { "name": "af2l1_8",  "pair": [42, 6],   "alg": "R D' R' U R U D R'" },
  { "name": "af2l1_9",  "pair": [41, 36],  "alg": "U R' U2 R U' R U R'" },
  { "name": "af2l1_10", "pair": [150, 18], "alg": "U' F U F2 U' F" },
  { "name": "af2l1_11", "pair": [166, 34], "alg": "U' L U' L' R U' R'" },
  { "name": "af2l1_12", "pair": [165, 33], "alg": "U2 R U2 R2 U' R2 U R'" },
  { "name": "af2l1_13", "pair": [22, 82],  "alg": "U' L F' L2 U L U2 F" },
  { "name": "af2l1_14", "pair": [38, 34],  "alg": "U2 R2 D B2 D' R2" },
  { "name": "af2l1_15", "pair": [150, 82], "alg": "U' R' D' F' D R" },
  { "name": "af2l1_16", "pair": [166, 98], "alg": "U2 L F' U' F L'" },
  { "name": "af2l1_17", "pair": [165, 97], "alg": "U R' U2 R F' U' F" },
  { "name": "af2l1_18", "pair": [86, 82],  "alg": "U' F U2 F' R U R'" },
  { "name": "af2l1_19", "pair": [102, 34], "alg": "U L U L' R U R'" },
  { "name": "af2l1_20", "pair": [101, 97], "alg": "U F D R D' F'" },
  { "name": "af2l1_21", "pair": [22, 18],  "alg": "R L' U2 L R'" },
  { "name": "af2l1_22", "pair": [38, 98],  "alg": "F' L U' L' F" },
  { "name": "af2l1_23", "pair": [37, 33],  "alg": "R' U R2 U' R'" },
  { "name": "af2l1_24", "pair": [26, 82],  "alg": "R' F R2 U' R2 F' R" },
  { "name": "af2l1_25", "pair": [42, 34],  "alg": "R L U2 L' R'" },
  { "name": "af2l1_26", "pair": [41, 97],  "alg": "F' R' U2 R U' F" },
  { "name": "af2l1_27", "pair": [90, 18],  "alg": "L' U L U R U R' U R U' R'" },
  { "name": "af2l1_28", "pair": [105, 33], "alg": "R' U R U' R U R' U R U' R'" },
  { "name": "af2l1_29", "pair": [154, 18], "alg": "R' F R U' R' F' R2 U R' U R U R'" },
  { "name": "af2l1_30", "pair": [170, 98], "alg": "L U' L' F' L F' L' F2" },
  { "name": "af2l1_31", "pair": [169, 33], "alg": "R' U R U R' U R2 U R'" },
  { "name": "af2l1_32", "pair": [90, 82],  "alg": "F U' R U' R' F' R U' R' U' R U R'" },
  { "name": "af2l1_33", "pair": [106, 34], "alg": "L U' L' U' L U L' R U' R'" },
  { "name": "af2l1_34", "pair": [105, 97], "alg": "R' U R2 U' R2 F R F' R U' R'" },
  { "name": "af2l1_35", "pair": [154, 82], "alg": "F U2 R U' R' F' U R U R'" },
  { "name": "af2l1_36", "pair": [170, 34], "alg": "L U' L' U' R U2 R' U R U' R'" },
  { "name": "af2l1_37", "pair": [169, 97], "alg": "R' U R L F' R' F R F L'" },
  { "name": "af2l1_38", "pair": [26, 18],  "alg": "F2 R' F2 D' R U' R' D R" },
  { "name": "af2l1_39", "pair": [42, 98],  "alg": "L U L' R U2 R' U F' U' F" },
  { "name": "af2l1_40", "pair": [41, 33],  "alg": "R' U R2 U2 R' U R' F R F'" },
  { "name": "af2l1_41", "pair": [90, 70],  "alg": "L' U' L F' U' F" },
  { "name": "af2l1_42", "pair": [106, 100], "alg": "L' B L B' R U2 R'" },
  { "name": "af2l1_43", "pair": [105, 69], "alg": "B' R B R' U2 R U' R'" },
  { "name": "af2l1_44", "pair": [154, 84], "alg": "U L' U L U' F R' F' R" },
  { "name": "af2l1_45", "pair": [170, 70], "alg": "U L U L' F' U F" },
  { "name": "af2l1_46", "pair": [169, 100], "alg": "U R' U R F' U F" },
  { "name": "af2l1_47", "pair": [26, 84],  "alg": "L F L' F L F' L'" },
  { "name": "af2l1_48", "pair": [42, 70],  "alg": "U2 L U' L' F' U2 F" },
  { "name": "af2l1_49", "pair": [150, 82], "alg": "U' F U' F' U R U' R'" },
  { "name": "af2l1_50", "pair": [166, 98], "alg": "U' L U L' U' F' U' F" }
]
